LICENSE.txt
MANIFEST.in
README.rst
setup.py
tox.ini
django_uuidstore.egg-info/PKG-INFO
django_uuidstore.egg-info/SOURCES.txt
django_uuidstore.egg-info/dependency_links.txt
django_uuidstore.egg-info/not-zip-safe
django_uuidstore.egg-info/requires.txt
django_uuidstore.egg-info/top_level.txt
docs/Makefile
docs/conf.py
docs/index.rst
docs/install.rst
docs/intro.rst
docs/make.bat
docs/requirements.txt
docs/_static/.empty
docs/_templates/.empty
example/__init__.py
example/manage.py
example/settings.py
example/urls.py
example/exampleapp/__init__.py
example/exampleapp/admin.py
example/exampleapp/models.py
uuidstore/__init__.py
uuidstore/admin.py
uuidstore/models.py
uuidstore/registry.py
uuidstore/migrations/0001_initial.py
uuidstore/migrations/__init__.py
uuidstore/south_migrations/0001_initial.py
uuidstore/south_migrations/__init__.py
uuidstore/tests/__init__.py
uuidstore/tests/models.py
uuidstore/tests/run.py
uuidstore/tests/test_uuid_models.py
uuidstore/tests/urls.py