Metadata-Version: 1.1
Name: django-uuidstore
Version: 0.1.0
Summary: Site-wide UUIDs for Django projects
Home-page: https://bitbucket.org/mhurt/django-uuidstore
Author: Mike Hurt
Author-email: mike@mhtechnical.net
License: MIT
Keywords: django uuid orm model utility
Platform: UNKNOWN
Classifier: Development Status :: 5 - Production/Stable
Classifier: Environment :: Web Environment
Classifier: Framework :: Django
Classifier: Intended Audience :: Developers
Classifier: License :: OSI Approved :: MIT License
Classifier: Operating System :: OS Independent
Classifier: Programming Language :: Python
Classifier: Topic :: Internet :: WWW/HTTP :: Dynamic Content
